odoo10_addon_maintenance_equipment_scrap-10.0.1.0.0-py2.7-nspkg.pth
odoo/addons/maintenance_equipment_scrap/README.rst
odoo/addons/maintenance_equipment_scrap/__init__.py
odoo/addons/maintenance_equipment_scrap/__manifest__.py
odoo/addons/maintenance_equipment_scrap/data/maintenance_data.xml
odoo/addons/maintenance_equipment_scrap/models/__init__.py
odoo/addons/maintenance_equipment_scrap/models/maintenance_equipment.py
odoo/addons/maintenance_equipment_scrap/models/maintenance_equipment_category.py
odoo/addons/maintenance_equipment_scrap/tests/__init__.py
odoo/addons/maintenance_equipment_scrap/tests/test_maintenance_equipment_scrap.py
odoo/addons/maintenance_equipment_scrap/views/maintenance_equipment.xml
odoo/addons/maintenance_equipment_scrap/views/maintenance_equipment_category.xml
odoo/addons/maintenance_equipment_scrap/wizard/__init__.py
odoo/addons/maintenance_equipment_scrap/wizard/scrap_equipment.py
odoo/addons/maintenance_equipment_scrap/wizard/scrap_equipment.xml
odoo10_addon_maintenance_equipment_scrap-10.0.1.0.0.dist-info/DESCRIPTION.rst
odoo10_addon_maintenance_equipment_scrap-10.0.1.0.0.dist-info/METADATA
odoo10_addon_maintenance_equipment_scrap-10.0.1.0.0.dist-info/RECORD
odoo10_addon_maintenance_equipment_scrap-10.0.1.0.0.dist-info/WHEEL
odoo10_addon_maintenance_equipment_scrap-10.0.1.0.0.dist-info/metadata.json
odoo10_addon_maintenance_equipment_scrap-10.0.1.0.0.dist-info/namespace_packages.txt
odoo10_addon_maintenance_equipment_scrap-10.0.1.0.0.dist-info/top_level.txt
